winshlex/__init__.py
winshlex/lex.py
winshlex-0.0.1.dist-info/LICENCE
winshlex-0.0.1.dist-info/METADATA
winshlex-0.0.1.dist-info/WHEEL
winshlex-0.0.1.dist-info/top_level.txt
winshlex-0.0.1.dist-info/RECORD
