Metadata-Version: 2.1
Name: winshlex
Version: 0.0.1
Summary: Alternative to python shlex package
Home-page: https://github.com/jdjebi/winshlex
Author: jdjebi
Author-email: tidev.99@gmail.com
License: UNKNOWN
Platform: UNKNOWN
Classifier: Programming Language :: Python :: 3
Classifier: License :: OSI Approved :: MIT License
Classifier: Operating System :: OS Independent
Requires-Python: >=3.3
